chitchat/__init__.py
chitchat/callbacks.py
chitchat/client.py
chitchat/connection.py
chitchat/constants.py
chitchat/exceptions.py
chitchat/utils.py
chitchat/messaging/__init__.py
chitchat/messaging/incoming.py
chitchat-0.0.1.dist-info/DESCRIPTION.rst
chitchat-0.0.1.dist-info/METADATA
chitchat-0.0.1.dist-info/RECORD
chitchat-0.0.1.dist-info/WHEEL
chitchat-0.0.1.dist-info/metadata.json
chitchat-0.0.1.dist-info/top_level.txt
